{
  "5111": "Düsseldorf",
  "5112": "Duisburg",
  "5113": "Essen",
  "5114": "Krefeld",
  "5116": "Mönchengladbach",
  "5117": "Mülheim a.d. Ruhr",
  "5119": "Oberhausen",
  "5120": "Remscheid",
  "5122": "Solingen",
  "5124": "Wuppertal",
  "5154": "Kreis Kleve",
  "5158": "Kreis Mettmann",
  "5162": "Rhein-Kreis Neuss",
  "5166": "Kreis Viersen",
  "5170": "Kreis Wesel",
  "5314": "Bonn",
  "5315": "Köln",
  "5316": "Leverkusen",
  "5334": "Städteregion Aachen",
  "5358": "Kreis Düren",
  "5362": "Rhein-Erft-Kreis",
  "5366": "Kreis Euskirchen",
  "5370": "Kreis Heinsberg",
  "5374": "Oberbergischer Kreis",
  "5378": "Rheinisch-Bergischer Kreis",
  "5382": "Rhein-Sieg-Kreis",
  "5512": "Bottrop",
  "5513": "Gelsenkirchen",
  "5515": "Münster",
  "5554": "Kreis Borken",
  "5558": "Kreis Coesfeld",
  "5562": "Kreis Recklinghausen",
  "5566": "Kreis Steinfurt",
  "5570": "Kreis Warendorf",
  "5711": "Bielefeld",
  "5754": "Kreis Gütersloh",
  "5758": "Kreis Herford",
  "5762": "Kreis Höxter",
  "5766": "Kreis Lippe",
  "5770": "Kreis Minden-Lübbecke",
  "5774": "Kreis Paderborn",
  "5911": "Bochum",
  "5913": "Dortmund",
  "5914": "Hagen",
  "5915": "Hamm",
  "5916": "Herne",
  "5954": "Ennepe-Ruhr-Kreis",
  "5958": "Hochsauerlandkreis",
  "5962": "Märkischer Kreis",
  "5966": "Kreis Olpe",
  "5970": "Kreis Siegen-Wittgenstein",
  "5974": "Kreis Soest",
  "5978": "Kreis Unna"
}